sh4dis/__init__.py
sh4dis/sh4.py
sh4dis-1.0.0.dist-info/LICENSE
sh4dis-1.0.0.dist-info/METADATA
sh4dis-1.0.0.dist-info/WHEEL
sh4dis-1.0.0.dist-info/top_level.txt
sh4dis-1.0.0.dist-info/RECORD
