Metadata-Version: 2.1
Name: sh4dis
Version: 1.0.0
Summary: SH4 disassembler library
Home-page: https://github.com/lwerdna/sh4dis
Author: Andrew Lamoureux
Author-email: foo@bar.com
License: UNKNOWN
Platform: UNKNOWN
Classifier: Programming Language :: Python :: 3
Classifier: License :: Public Domain
Classifier: Operating System :: OS Independent
